agi_med_exp/__init__.py
agi_med_exp/config/__init__.py
agi_med_exp/config/config.py
agi_med_exp/config/env_loader.py
agi_med_exp/datasets/__init__.py
agi_med_exp/datasets/digital_assistant_dataset.py
agi_med_exp-2.1.0.dist-info/METADATA
agi_med_exp-2.1.0.dist-info/WHEEL
agi_med_exp-2.1.0.dist-info/top_level.txt
agi_med_exp-2.1.0.dist-info/RECORD
