Metadata-Version: 2.2
Name: agi_med_exp
Version: 2.1.0
Summary: Exp utils for agi-med team
Author: AGI-MED-TEAM
Requires-Python: >=3.13
Requires-Dist: pyyaml~=6.0.2
Requires-Dist: agi-med-common==2.1.0
Requires-Dist: types-PyYAML~=6.0.12.20240917
